pygarden/__init__.py
pygarden/auth.py
pygarden/crud_table.py
pygarden/database.py
pygarden/env.py
pygarden/error_codes.py
pygarden/exceptions.py
pygarden/file_operations.py
pygarden/gen.py
pygarden/llama_cpp.py
pygarden/logz.py
pygarden/mail.py
pygarden/cli/README.md
pygarden/cli/__init__.py
pygarden/cli/docker_cli.py
pygarden/cli/gen_cli.py
pygarden/cli/python_cli.py
pygarden/mixins/README.md
pygarden/mixins/__init__.py
pygarden/mixins/asyncpg_mixin.py
pygarden/mixins/influx.py
pygarden/mixins/minio_mixin.py
pygarden/mixins/mssql.py
pygarden/mixins/multiple.py
pygarden/mixins/pandas_mixin.py
pygarden/mixins/postgres.py
pygarden/mixins/postgres_logger.py
pygarden/mixins/sqlite.py
pygarden/scrapers/__init__.py
pygarden/scrapers/connections.py
pygarden/scrapers/csvs.py
pygarden/scrapers/scraper.py
pygarden/scrapers/seleniumscraper.py
pygarden/scrapers/static.py
pygarden/scrapers/webdriver.py
pygarden/scrapers/mixins/README.md
pygarden/scrapers/mixins/__init__.py
pygarden/scrapers/mixins/arcgis.py
pygarden/scrapers/mixins/cfscrape.py
pygarden/scrapers/mixins/cloudscraper.py
pygarden/scrapers/mixins/html.py
pygarden/scrapers/mixins/html_soup.py
pygarden/scrapers/mixins/json.py
pygarden/scrapers/mixins/request.py
pygarden/scrapers/mixins/websocket.py
pygarden/scrapers/mixins/xml.py
pygarden/scrapers/mixins/xml_soup.py
pygarden-0.3.27.dist-info/METADATA
pygarden-0.3.27.dist-info/WHEEL
pygarden-0.3.27.dist-info/entry_points.txt
pygarden-0.3.27.dist-info/licenses/LICENSE
pygarden-0.3.27.dist-info/RECORD
