Metadata-Version: 2.4
Name: pygarden
Version: 0.3.27
Summary: Package to perform everyday tasks - logging, accessing database, etc.
Project-URL: Source, https://code.ornl.gov/pygarden/pygarden
Author: Alec Hamaker
Author-email: "Grant, Josh" <grantjn@ornl.gov>, Jonathan Huihui <huihuijk@ornl.gov>, Bhaskar Bishnoi <bishnoib@ornl.gov>, Kyle Medlen <medlenwk@ornl.gov>, Midgie MacFarland <macfarlandmj@ornl.gov>, Chris Tester <testercb@ornl.gov>, Jacob Isber <isberj@ornl.gov>, Mitchell Broughton <broxsonmr@ornl.gov>
License: Copyright 2021 ORNL
License-File: LICENSE
Keywords: database,logging,mixins,mysqlmixin,pandasmixin,postgresmixin
Classifier: Intended Audience :: Developers
Classifier: Programming Language :: Python
Classifier: Programming Language :: Python :: 3
Classifier: Programming Language :: Python :: 3.10
Classifier: Programming Language :: Python :: 3.11
Classifier: Programming Language :: Python :: 3.12
Classifier: Programming Language :: Python :: 3.13
Classifier: Programming Language :: Python :: 3.14
Classifier: Topic :: Software Development :: Build Tools
Classifier: Topic :: Software Development :: Libraries
Classifier: Topic :: Software Development :: Libraries :: Application Frameworks
Classifier: Topic :: Software Development :: Libraries :: Python Modules
Requires-Python: <3.15,>=3.10
Requires-Dist: loguru>=0.7.2
Requires-Dist: rich>=13.7.1
Provides-Extra: all
Requires-Dist: asyncpg; extra == 'all'
Requires-Dist: beautifulsoup4~=4.10.0; extra == 'all'
Requires-Dist: cfscrape~=2.1.1; extra == 'all'
Requires-Dist: click==8.0.3; extra == 'all'
Requires-Dist: cloudscraper~=1.2.60; extra == 'all'
Requires-Dist: flask>=2.0.2; extra == 'all'
Requires-Dist: influxdb==5.3.1; extra == 'all'
Requires-Dist: ldap3==2.9.1; extra == 'all'
Requires-Dist: minio~=7.1.0; extra == 'all'
Requires-Dist: pandas==2.1.4; extra == 'all'
Requires-Dist: psycopg[binary]>=3.0.0; extra == 'all'
Requires-Dist: pymssql>=2.3.7; extra == 'all'
Requires-Dist: requests~=2.27.1; extra == 'all'
Requires-Dist: rich==13.7.1; extra == 'all'
Requires-Dist: selenium~=4.1.3; extra == 'all'
Requires-Dist: sqlalchemy~=2.0.23; extra == 'all'
Requires-Dist: urllib3~=1.26.9; extra == 'all'
Requires-Dist: websocket~=0.2.1; extra == 'all'
Provides-Extra: auth
Requires-Dist: flask>=2.0.2; extra == 'auth'
Requires-Dist: ldap3==2.9.1; extra == 'auth'
Provides-Extra: cli
Requires-Dist: click==8.0.3; extra == 'cli'
Requires-Dist: rich==13.7.1; extra == 'cli'
Provides-Extra: db-pandas
Requires-Dist: pandas==2.1.4; extra == 'db-pandas'
Requires-Dist: sqlalchemy~=2.0.23; extra == 'db-pandas'
Provides-Extra: dev
Requires-Dist: bumpversion>=0.6.0; extra == 'dev'
Requires-Dist: moto==5.0.11; extra == 'dev'
Requires-Dist: pytest-asyncio>=0.23.0; extra == 'dev'
Requires-Dist: pytest-cov==5.0.0; extra == 'dev'
Requires-Dist: pytest-postgresql>=6.0.0; extra == 'dev'
Requires-Dist: pytest==8.3.1; extra == 'dev'
Requires-Dist: python-hcl2==7.1.0; extra == 'dev'
Requires-Dist: ruff==0.5.4; extra == 'dev'
Requires-Dist: testcontainers[mssql]>=4.8.0; extra == 'dev'
Provides-Extra: influx
Requires-Dist: influxdb==5.3.1; extra == 'influx'
Provides-Extra: llama
Requires-Dist: llama-cpp-python==0.2.74; extra == 'llama'
Provides-Extra: minio
Requires-Dist: minio~=7.1.0; extra == 'minio'
Provides-Extra: mssql
Requires-Dist: pymssql>=2.3.7; extra == 'mssql'
Provides-Extra: postgres
Requires-Dist: asyncpg; extra == 'postgres'
Requires-Dist: psycopg[binary]>=3.0.0; extra == 'postgres'
Provides-Extra: scrapers
Requires-Dist: beautifulsoup4~=4.10.0; extra == 'scrapers'
Requires-Dist: cfscrape~=2.1.1; extra == 'scrapers'
Requires-Dist: cloudscraper~=1.2.60; extra == 'scrapers'
Requires-Dist: pandas==2.1.4; extra == 'scrapers'
Requires-Dist: requests~=2.27.1; extra == 'scrapers'
Requires-Dist: selenium~=4.1.3; extra == 'scrapers'
Requires-Dist: urllib3~=1.26.9; extra == 'scrapers'
Requires-Dist: websocket~=0.2.1; extra == 'scrapers'
